circum_kinect/__init__.py
circum_kinect/kinect.py
circum_kinect-0.0.0.dist-info/LICENSE
circum_kinect-0.0.0.dist-info/METADATA
circum_kinect-0.0.0.dist-info/WHEEL
circum_kinect-0.0.0.dist-info/entry_points.txt
circum_kinect-0.0.0.dist-info/top_level.txt
circum_kinect-0.0.0.dist-info/RECORD
