Metadata-Version: 2.1
Name: circum-kinect
Version: 0.0.0
Summary: Kinect sensor plugin for circum.
Home-page: https://github.com/LumineerLabs/circum-kinect
Author: Lane Haury
Author-email: lane@lumineerlabs.com
License: UNKNOWN
Platform: UNKNOWN
Classifier: License :: OSI Approved :: MIT License
Classifier: Programming Language :: Python
Classifier: Operating System :: OS Independent
Requires-Dist: circum
Requires-Dist: click
Requires-Dist: setuptools-git-version
